{
  "name": "Nathan Moody",
  "age": 42,
  "address": {
    "street": "Baslav Path",
    "city": "Gagzujit",
    "state": "NE",
    "zip": "30507"
  },
  "contact": {
    "phone": "(735) 276-4631",
    "servicePhone": "800567549"
  },
  "birthday": "1973-07-02T02:31:50.300Z",
  "ip": "141.173.141.245",
  "foo": "bar",
  "profile": {
    "about": "Devdupek imawaf riac sossuc gulnac gewa pumnilkus vusa buup ru newnuij ar. Id lipob zepor maraso eto cob ufele ce jesug ozal dopsopij hanweej gubsimuf faka edoh zerpepzip po wecwihgi. Jelnew dabi mudemva fenuwzu suju dek pesup onuew eldop huwu oko alonedpod res lugarhuv hov to zaz. Tehimu kulotsus sudo wuhcosmus ikhukri evbi gupnasmum kihmi eric jifte us epe sigalur rububtu. Bimez sorba zamehelu deftouva dadlagab owpo agobewe valuz uwicezu osoek bafu etosudgum nulbufcul juk.",
    "bio": "Tuh zalav gu vemdaje ba ruv jekcook ti cu atuvpob idoma ojnojle pi ku. Se utho vo im rukutti gocatgoc zuhut cu mavuciw mic budboso kingazo we pojdid efu kaozeso rif olatoune. Riw ro jicu nu ve ociwumlu ubnelo capi wimicar ebvako cis nasof as kenveos bosnefa. Voh zeb ul foluug me hierebef fevsomzo danok gif ge foz daolaro uvli. Avob five don od dijud minviwep civcikvo re pivwi civu wug zijil apo ohu roksaho kujbul. Lizhi ewpudfat pajcepji irejaca oj don tomij ubmo anjah obizojse wi asguz ruwupa nav ela zizif."
  },
  "apiKey": "6ef284e1ffd72f0146fc197f2923f30a8f7492690cacd25536cb7bff5828c947",
  "currency": {
    "code": "PLN",
    "name": "Poland Zloty"
  }
}